badgrclient/__init__.py
badgrclient/badgrclient.py
badgrclient/badgrmodels.py
badgrclient/exceptions.py
badgrclient/util.py
badgrclient-0.1.2.dist-info/LICENSE
badgrclient-0.1.2.dist-info/METADATA
badgrclient-0.1.2.dist-info/WHEEL
badgrclient-0.1.2.dist-info/top_level.txt
badgrclient-0.1.2.dist-info/RECORD
