Metadata-Version: 2.1
Name: badgrclient
Version: 0.1.2
Summary: A python library for Badgr APIs
Home-page: https://github.com/snehalbaghel/badgrclient
Author: Snehal Baghel
Author-email: snehalbaghel@gmail.com
License: GNU General Public License v3.0
Keywords: badgr,openbadges,api,library
Platform: UNKNOWN
Classifier: Intended Audience :: Developers
Classifier: Intended Audience :: Information Technology
Classifier: License :: OSI Approved :: GNU General Public License v3 (GPLv3)
Classifier: Programming Language :: Python :: 3
Classifier: Topic :: Software Development :: Libraries
Requires-Dist: requests
Requires-Dist: python-dotenv (==0.14.0)
